{
  "timestamp_utc": "2025-09-21T02:17:05.897625",
  "memory_type": "STM",
  "category": "mindx_agint/cycles",
  "metadata": {
    "agent": "mindx_agint",
    "component": "cognitive_loop",
    "timestamp": 1758421025.8973882
  },
  "data": {
    "cycle": 1,
    "max_cycles": 8,
    "directive": "evolve test-ui.html",
    "autonomous_mode": false,
    "timestamp": 1758421025.8973753,
    "status": "completed",
    "phase": "cycle_complete",
    "cycle_duration": 5.560565948486328,
    "code_changes_count": 0,
    "code_changes_summary": []
  }
}