{
  "timestamp_utc": "2026-02-25T02:07:16.227581",
  "memory_type": "STM",
  "category": "mindx_agint/cycles",
  "metadata": {
    "agent": "mindx_agint",
    "component": "cognitive_loop",
    "timestamp": 1771985236.2274446
  },
  "data": {
    "cycle": 5,
    "max_cycles": 8,
    "directive": "evolve",
    "autonomous_mode": false,
    "timestamp": 1771985236.227439,
    "status": "completed",
    "phase": "cycle_complete",
    "cycle_duration": 5.564709663391113,
    "code_changes_count": 0,
    "code_changes_summary": []
  }
}